cut_finder/__init__.py
cut_finder/__main__.py
cut_finder/board_sets.py
cut_finder/boards.py
cut_finder/cutfinder.py
cut_finder-0.1.0.dist-info/LICENSE
cut_finder-0.1.0.dist-info/METADATA
cut_finder-0.1.0.dist-info/WHEEL
cut_finder-0.1.0.dist-info/entry_points.txt
cut_finder-0.1.0.dist-info/top_level.txt
cut_finder-0.1.0.dist-info/RECORD
